Data_Memory.vhdl
library IEEE;
use IEEE.STD_LOGIC_1164.ALL;
USE IEEE.numeric_std.all;  
-- VHDL code for the data Memory of the MIPS Processor
entity Data_Memory is
port (
 clk: in std_logic;
 mem_access_addr: in std_logic_Vector(15 downto 0);
 mem_write_data: in std_logic_Vector(15 downto 0);
 mem_write_en,mem_read:in std_logic;
 mem_read_data: out std_logic_Vector(15 downto 0)
);
end Data_Memory;

architecture Behavioral of Data_Memory is
signal i: integer;
signal ram_addr: std_logic_vector(7 downto 0);
type data_mem is array (0 to 255 ) of std_logic_vector (15 downto 0);
signal RAM: data_mem :=((others=> (others=>'0')));
begin

 ram_addr <= mem_access_addr(7 downto 0);
 process(clk)
 begin
  if(rising_edge(clk)) then
  if (mem_write_en='1') then
  ram(to_integer(unsigned(ram_addr))) <= mem_write_data;
  end if;
  end if;
 end process;
   mem_read_data <= ram(to_integer(unsigned(ram_addr))) when (mem_read='1') else x"0000";

end Behavioral;

alu_16bit.vhdl
library IEEE;
use IEEE.STD_LOGIC_1164.ALL;
use IEEE.NUMERIC_STD.ALL;
entity alu_16bit is
    Port 
    ( 
        inp_a,inp_b : in STD_LOGIC_VECTOR(15 downto 0);
        sel : in STD_LOGIC_VECTOR (2 downto 0);
        out_alu : out STD_LOGIC_VECTOR(15 downto 0);
        zero_flag : out STD_LOGIC;
        carry_flag : out STD_LOGIC
    );
end alu_16bit;
 
architecture Behavioral of alu_16bit is
    signal result:std_logic_vector(16 downto 0);
    begin
    process(inp_a, inp_b, sel)
        begin
        case sel is
            when "000" =>
            result<= '0'& std_logic_vector(unsigned(inp_a) + unsigned(inp_b)); --addition
            when "001" =>
            result<= std_logic_vector (('0' & unsigned(inp_a)) - ('0' & unsigned(inp_b))); --subtraction
            when "010" =>
            result<= '0' & std_logic_vector((unsigned(inp_a(7 downto 0))) * (unsigned(inp_b(7 downto 0)))); --multiplication
            when "011" =>
            result<= '0' & std_logic_vector((unsigned(inp_a)) / (unsigned(inp_b))); --division
            when "100" =>
            result<='0' & (inp_a and inp_b); --AND gate
            when "101" =>
            result<= '0' & (inp_a or inp_b); --OR gate
            when "110" =>
            result<= std_logic_vector (('0' & unsigned(inp_a)) + 1) ; --increment inp_a
            when "111" =>
            result<= std_logic_vector (('0' & unsigned(inp_a)) - 1) ; --decrement inp_a
            when others => NULL;
        end case;
        
    end process;
    zero_flag<='1' when result(15 downto 0)<=x"0000" else '0';
    carry_flag<=result(16);
    out_alu<= result(15 downto 0);
end Behavioral;

alu_control.vhdl
library IEEE;
use IEEE.STD_LOGIC_1164.ALL;
use IEEE.NUMERIC_STD.ALL;

entity alu_control is 
    port 
    (
        alu_select: out std_logic_vector(2 downto 0);
        aluop:in std_logic_vector(1 downto 0);
        funct:in std_logic_vector (2 downto 0)

    );
end alu_control;

architecture Behavioral of alu_control is

begin
    process(aluop,funct)
    begin
        case aluop is 
            when "00"=>
            alu_select <= funct(2 downto 0);
            when "01"=>
            alu_select <= "001";
            when "10"=>
            alu_select <= "100";
            when "11"=>
            alu_select <= "000";
            when others =>
            alu_select <= "000";
        end case;
    end process;
end Behavioral;

register_file.vhdl
library IEEE;
use IEEE.STD_LOGIC_1164.ALL;
USE IEEE.numeric_std.all;  
-- VHDL code for the register file of the MIPS Processor
entity register_file is
port (
 clk,rst: in std_logic;
 reg_write_en: in std_logic;
 reg_write_dest: in std_logic_vector(2 downto 0);
 reg_write_data: in std_logic_vector(15 downto 0);
 reg_read_addr_1: in std_logic_vector(2 downto 0);
 reg_read_data_1: out std_logic_vector(15 downto 0);
 reg_read_addr_2: in std_logic_vector(2 downto 0);
 reg_read_data_2: out std_logic_vector(15 downto 0)
);
end register_file;

architecture Behavioral of register_file is
type reg_type is array (0 to 7 ) of std_logic_vector (15 downto 0);
signal reg_array: reg_type;
begin
 process(clk,rst) 
 begin
 if(rst='1') then
   reg_array(0) <= x"0000";
   reg_array(1) <= x"0000";
   reg_array(2) <= x"0000";
   reg_array(3) <= x"0000";
   reg_array(4) <= x"0000";
   reg_array(5) <= x"0000";
   reg_array(6) <= x"0000";
   reg_array(7) <= x"0000";
 elsif(rising_edge(clk)) then
   if(reg_write_en='1') then
    reg_array(to_integer(unsigned(reg_write_dest))) <= reg_write_data;
   end if;
 end if;
 end process;

 reg_read_data_1 <= x"0000" when reg_read_addr_1 = "000" else reg_array(to_integer(unsigned(reg_read_addr_1)));
 reg_read_data_2 <= x"0000" when reg_read_addr_2 = "000" else reg_array(to_integer(unsigned(reg_read_addr_2)));

end Behavioral;

Control_unit.vhdl
library IEEE;
use IEEE.STD_LOGIC_1164.ALL;
USE IEEE.numeric_std.all;  
-- VHDL code for Control Unit of the MIPS Processor
entity Control_unit is
port (
  opcode: in std_logic_vector(3 downto 0);
  reset: in std_logic;
  reg_dst,mem_to_reg,alu_op: out std_logic_vector(1 downto 0);
  jump,branch,mem_read,mem_write,alu_src,reg_write,sign_or_zero: out std_logic
 );
end Control_unit;

architecture behavioral of Control_unit is

begin
    process(reset,opcode)
    begin
        if(reset = '1') then
            reg_dst <= "00";
            mem_to_reg <= "00";
            alu_op <= "00";
            jump <= '0';
            branch <= '0';
            mem_read <= '0';
            mem_write <= '0';
            alu_src <= '0';
            reg_write <= '0';
            sign_or_zero <= '1';
        else 
        -- reg_write <= '0'; --set the register_write to zero every time an instruction is decoded
            case opcode is
                when"0001" => --R-Type instruction
                    reg_dst <= "01";
                    mem_to_reg <= "00";
                    alu_op <= "00";
                    jump <= '0';
                    branch <= '0';
                    mem_read <= '0';
                    mem_write <= '0';
                    alu_src <= '0';
                    reg_write <= '1';
                    sign_or_zero <= '1';
                when"0010" => --I-Type add immediate
                    reg_dst <= "00";
                    mem_to_reg <= "00";
                    alu_op <= "11";
                    jump <= '0';
                    branch <= '0';
                    mem_read <= '0';
                    mem_write <= '0';
                    alu_src <= '1';
                    reg_write <= '1';
                    sign_or_zero <= '1';
                when"0011" => --I-Type subtract immediate
                    reg_dst <= "00";
                    mem_to_reg <= "00";
                    alu_op <= "01";
                    jump <= '0';
                    branch <= '0';
                    mem_read <= '0';
                    mem_write <= '0';
                    alu_src <= '1';
                    reg_write <= '1';
                    sign_or_zero <= '1';
                when"0100" => --I-Type and immediate
                    reg_dst <= "00";
                    mem_to_reg <= "00";
                    alu_op <= "10";
                    jump <= '0';
                    branch <= '0';
                    mem_read <= '0';
                    mem_write <= '0';
                    alu_src <= '1';
                    reg_write <= '1';
                    sign_or_zero <= '1';
                when"0111" => --load immediate value
                    reg_dst <= "11";
                    mem_to_reg <= "00";
                    alu_op <= "11";
                    jump <= '0';
                    branch <= '0';
                    mem_read <= '1';
                    mem_write <= '0';
                    alu_src <= '1';
                    reg_write <= '1'; --after 10 ns
                    sign_or_zero <= '1';
                when"1000" => --load from memory
                    reg_dst <= "00";
                    mem_to_reg <= "01";
                    alu_op <= "11"; -- alu will add during ld adn st instructions
                    jump <= '0';
                    branch <= '0';
                    mem_read <= '1';
                    mem_write <= '0';
                    alu_src <= '0';
                    reg_write <= '1'; --after 10 ns
                    sign_or_zero <= '1';
                when"1001" => --store to memory
                    reg_dst <= "10"; --don't care
                    mem_to_reg <= "XX"; --don't care
                    alu_op <= "11"; --
                    jump <= '0';
                    branch <= '0';
                    mem_read <= '0'; 
                    mem_write <= '1';
                    alu_src <= '0';
                    reg_write <= '0';
                    sign_or_zero <= '1';
                when"1010" => --j-type Branch if equal
                    reg_dst <= "00";
                    mem_to_reg <= "00";
                    alu_op <= "01"; --subtract
                    jump <= '0';
                    branch <= '1';
                    mem_read <= '0';
                    mem_write <= '0';
                    alu_src <= '0';
                    reg_write <= '0';
                    sign_or_zero <= '1';
                when"1011" => --j-type Branch if greater than
                    reg_dst <= "00";
                    mem_to_reg <= "00";
                    alu_op <= "01"; --subtract
                    jump <= '0';
                    branch <= '1';
                    mem_read <= '0';
                    mem_write <= '0';
                    alu_src <= '0';
                    reg_write <= '0';
                    sign_or_zero <= '1';
                when"1100" => --j-type Branch if less than
                    reg_dst <= "00";
                    mem_to_reg <= "00";
                    alu_op <= "01"; --subtract
                    jump <= '0';
                    branch <= '1';
                    mem_read <= '0';
                    mem_write <= '0';
                    alu_src <= '0';
                    reg_write <= '0';
                    sign_or_zero <= '1';
                when"1101" => --j-type Branch on carry
                    reg_dst <= "10";
                    mem_to_reg <= "00";
                    alu_op <= "XX"; --subtract
                    jump <= '0';
                    branch <= '1';
                    mem_read <= '0';
                    mem_write <= '0';
                    alu_src <= '0';
                    reg_write <= '0';
                    sign_or_zero <= '1';
                when"1110" => --j-type Branch on zero
                    reg_dst <= "00";
                    mem_to_reg <= "00";
                    alu_op <= "01"; --subtract
                    jump <= '0';
                    branch <= '1';
                    mem_read <= '0';
                    mem_write <= '0';
                    alu_src <= '0';
                    reg_write <= '0';
                    sign_or_zero <= '1';
                when"1111" => --j-Type jump
                    reg_dst <= "XX";
                    mem_to_reg <= "XX";
                    alu_op <= "11"; --
                    mem_read <= '0';
                    jump <= '1';
                    branch <= '0';
                    mem_write <= '0';
                    alu_src <= '0';
                    reg_write <= '0';
                    sign_or_zero <= '1';
                when others => 
                    reg_dst <= "00";
                    mem_to_reg <= "00";
                    alu_op <= "00";
                    jump <= '0';
                    branch <= '0';
                    mem_read <= '0';
                    mem_write <= '0';
                    alu_src <= '0';
                    reg_write <= '0';
                    sign_or_zero <= '0';
            end case;        
        end if;    
    end process;
end behavioral;

Instruction_Memory.vhdl
library IEEE;
use IEEE.STD_LOGIC_1164.ALL;
USE IEEE.numeric_std.all;  
-- VHDL code for the Instruction Memory of the MIPS Processor
entity Instruction_Memory is
port (
 pc: in std_logic_vector(15 downto 0);
 instruction: out  std_logic_vector(15 downto 0)
);
end Instruction_Memory;

architecture Behavioral of Instruction_Memory is
signal rom_addr: std_logic_vector(3 downto 0);

 type ROM_type is array (0 to 15 ) of std_logic_vector(15 downto 0);
 constant rom_data: ROM_type:=(
   "0111001000000101", --0
   "0111010000000000", --1
   "0111011000000000", --2
   "0111100000000000", --3
   "0001010011010000", --4
   "0001000011011110", --5
   "0001000100100110", --6
   "1011011001000100", --7
   "0001100010010011", --8
   "0000000000000000",
   "0000000000000000", 
   "0000000000000000", 
   "0000000000000000", 
   "0000000000000000", 
   "0000000000000000", 
   "0000000000000000"  
  );
begin

 rom_addr <= pc(3 downto 0);
 instruction <= rom_data(to_integer(unsigned(rom_addr))) when pc < x"0010" else x"0000";

end Behavioral;

MIPS.vhdl
library IEEE;
use IEEE.STD_LOGIC_1164.ALL;
use IEEE.NUMERIC_STD.ALL;
entity mips is
    port
    (
        clk,reset: in std_logic;
        pc_out,alu_result: out std_logic_vector(15 downto 0)
    );
end mips;



architecture behavioral of mips is
    signal pc_current: std_logic_vector(15 downto 0);
    signal pc_next,pc2: std_logic_vector(15 downto 0);
    signal instr: std_logic_vector(15 downto 0);
    signal reg_dst,mem_to_reg,alu_op: std_logic_vector(1 downto 0);
    signal jump,branch,mem_read,mem_write,alu_src,reg_write: std_logic;
    signal reg_write_dest: std_logic_vector(2 downto 0);
    signal reg_write_data: std_logic_vector(15 downto 0);
    signal reg_read_addr_1: std_logic_vector(2 downto 0);
    signal reg_read_data_1: std_logic_vector(15 downto 0);
    signal reg_read_addr_2: std_logic_vector(2 downto 0);
    signal reg_read_data_2: std_logic_vector(15 downto 0);
    signal sign_ext_im,read_data2,zero_ext_im,imm_ext: std_logic_vector(15 downto 0);
    signal JRControl: std_logic;
    signal ALU_Control: std_logic_vector(2 downto 0);
    signal ALU_out: std_logic_vector(15 downto 0);
    signal zero_flag,carry_flag: std_logic;
    signal im_shift_1, PC_j, PC_beq, PC_4beq,PC_4beqj,PC_jr: std_logic_vector(15 downto 0);
    signal beq_control: std_logic;
    signal jump_shift_1: std_logic_vector(14 downto 0);
    signal AR,mem_read_data: std_logic_vector(15 downto 0);
    signal no_sign_ext: std_logic_vector(15 downto 0);
    signal sign_or_zero: std_logic;
    signal tmp1: std_logic_vector(6 downto 0);
    signal tmp2: std_logic_vector(9 downto 0);
    signal z: std_logic_vector(15 downto 0):= x"0001";
    signal FR: std_logic_vector(7 downto 0);
    -- type reg_type is array (0 to 1) of std_logic_vector (7 downto 0);
    -- signal FR: reg_type;
begin
    process(clk,reset)
    begin
        if(reset='1') then
            pc_current <= x"0000";
            -- FR <= x"00";
        elsif(rising_edge(clk)) then
            pc_current <= pc_next;
        end if;
    end process;
    pc2 <= std_logic_vector ( unsigned (pc_current) + unsigned (z) );

    Instruction_Memory: entity work.Instruction_Memory
    port map
    (
    pc => pc_current,
    Instruction => instr
    );

    jump_shift_1 <= instr(13 downto 0) & '0';

    control: entity work.Control_unit
    port map
    (
        reset => reset,
        opcode => instr(15 downto 12),
        reg_dst => reg_dst,
        mem_to_reg => mem_to_reg,
        alu_op => alu_op,
        jump => jump,
        branch => branch,
        mem_read => mem_read,
        mem_write => mem_write,
        alu_src => alu_src,
        reg_write => reg_write,
        sign_or_zero => sign_or_zero
    );
    --regdest multiplexer
    reg_write_dest <= "111" when  reg_dst= "10" else --keda keda malhash lazma bec reg_write='0' when dest="10"
        instr(5 downto 3) when  reg_dst= "01" else
        instr(11 downto 9);
    -- register file instantiation of the MIPS Processor
    reg_read_addr_1 <= "000" when reg_dst="10" else -- reg_dst="10" store to memory from one register only
    "000" when reg_dst="11" else instr(8 downto 6); 
    reg_read_addr_2 <= instr(11 downto 9);
    register_file: entity work.register_file
    port map
    (
        clk => clk,
        rst => reset,
        reg_write_en => reg_write,
        reg_write_dest => reg_write_dest,
        reg_write_data => reg_write_data,
        reg_read_addr_1 => reg_read_addr_1,
        reg_read_data_1 => reg_read_data_1,
        reg_read_addr_2 => reg_read_addr_2,
        reg_read_data_2 => reg_read_data_2
    );

    -- sign extend
    tmp1 <= (others => instr(8));
    tmp2 <= (others => instr(5));
    sign_ext_im <=  (tmp1 & instr(8 downto 0)) when instr(15 downto 12) = "0111" else (tmp2 & instr(5 downto 0)); 
    zero_ext_im <= ("0000000"& instr(8 downto 0)) when instr(15 downto 12) = "0111" else ("0000000000"& instr(5 downto 0)); 
    imm_ext <= sign_ext_im when sign_or_zero='1' else zero_ext_im;

    -- JR control unit of the MIPS
    JRControl <= '1' when ((alu_op="00") and (instr(3 downto 0)="1000")) else '0';

    ALUControl: entity work.alu_control 
    port map
    (   
        aluop => alu_op,
        funct => instr(2 downto 0),
        alu_select => ALU_Control
    );
    
    --alu_src multiplexer 
    read_data2 <= imm_ext when alu_src='1' else reg_read_data_2;
    
    alu: entity work.alu_16bit 
    port map
    (
        inp_a => reg_read_data_1,
        inp_b => read_data2,
        sel => ALU_Control,
        out_alu => ALU_out,
        zero_flag => zero_flag,
        carry_flag => carry_flag
    );
    FR(0) <= zero_flag  when instr(15 downto 12) = "0001";
    -- or "0010" or "0011" or "0100" ) ;
    FR(1) <= carry_flag when instr(15 downto 12) = "0001";
    -- or "0010" or "0011" or "0100" ) ;

    beq_control<=(branch and zero_flag) when instr(15 downto 12)="1010" else
    (branch and ALU_out(15)) when instr(15 downto 12) ="1100" else
    (branch and not (ALU_out(15))) when instr(15 downto 12) ="1011" else
    (branch and FR(1)) when instr(15 downto 12)="1101" else
    (branch and FR(0)) when instr(15 downto 12)="1110" else '0';
    --(branch and carry_flag) when instr(15 downto 12)="1100" else 
    --(branch and (not (carry_flag))) when instr(15 downto 12)="1011" else '0';
    pc_beq<= ("0000000000" & instr(5 downto 0)) when beq_control = '1' else ("0000" & instr(11 downto 0)) when jump = '1' else pc2 ;
    pc_next <= pc_beq;
    Ar<=("00000000" & instr(7 downto 0));
    data_memory: entity work.Data_Memory 
    port map
    (
        clk => clk,
        mem_access_addr => Ar,
        mem_write_data => reg_read_data_2,
        mem_write_en => mem_write,
        mem_read => mem_read,
        mem_read_data => mem_read_data
    );
    
    reg_write_data <= pc2 when (mem_to_reg = "10") else
    mem_read_data when (mem_to_reg = "01") else ALU_out;

    -- output
    pc_out <= pc_current;
    alu_result <= ALU_out;

end behavioral;

MIPS_TB.vhdl
LIBRARY ieee;
USE ieee.std_logic_1164.ALL;
-- fpga4student.com: FPGA projects, Verilog projects, VHDL projects
-- VHDL project: VHDL code for single-cycle MIPS Processor
-- VHDL testbench code for single-cycle MIPS Processor
ENTITY MIPS_TB IS
END MIPS_TB;
 
ARCHITECTURE behavior OF MIPS_TB IS 
    -- Component Declaration for the single-cycle MIPS Processor in VHDL
    COMPONENT MIPS
    PORT(
         clk : IN  std_logic;
         reset : IN  std_logic;
         pc_out : OUT  std_logic_vector(15 downto 0);
         alu_result : OUT  std_logic_vector(15 downto 0)
        );
    END COMPONENT;
   --Inputs
   signal clk : std_logic := '0';
   signal reset : std_logic := '0';
   --Outputs
   signal pc_out : std_logic_vector(15 downto 0);
   signal alu_result : std_logic_vector(15 downto 0);
   -- Clock period definitions
   constant clk_period : time := 10 ns;
BEGIN
 -- Instantiate the for the single-cycle MIPS Processor in VHDL
   uut: MIPS PORT MAP (
          clk => clk,
          reset => reset,
          pc_out => pc_out,
          alu_result => alu_result
        );

   -- Clock process definitions
   clk_process :process
   begin
  clk <= '0';
  wait for clk_period/2;
  clk <= '1';
  wait for clk_period/2;
   end process;
   -- Stimulus process
   stim_proc: process
   begin  
      reset <= '1';
      wait for 20 ns;
  reset <= '0';
      -- insert stimulus here 
      wait;
   end process;

END;

PROJECT_SIM.vcd
$date
  Sun Dec 24 21:26:40 2023
$end
$version
  GHDL v0
$end
$timescale
  1 fs
$end
$scope module standard $end
$upscope $end
$scope module std_logic_1164 $end
$upscope $end
$scope module numeric_std $end
$upscope $end
$scope module mips_tb $end
$var reg 1 ! clk $end
$var reg 1 " reset $end
$var reg 16 # pc_out[15:0] $end
$var reg 16 $ alu_result[15:0] $end
$scope module uut $end
$var reg 1 % clk $end
$var reg 1 & reset $end
$var reg 16 ' pc_out[15:0] $end
$var reg 16 ( alu_result[15:0] $end
$var reg 16 ) pc_current[15:0] $end
$var reg 16 * pc_next[15:0] $end
$var reg 16 + pc2[15:0] $end
$var reg 16 , instr[15:0] $end
$var reg 2 - reg_dst[1:0] $end
$var reg 2 . mem_to_reg[1:0] $end
$var reg 2 / alu_op[1:0] $end
$var reg 1 0 jump $end
$var reg 1 1 branch $end
$var reg 1 2 mem_read $end
$var reg 1 3 mem_write $end
$var reg 1 4 alu_src $end
$var reg 1 5 reg_write $end
$var reg 3 6 reg_write_dest[2:0] $end
$var reg 16 7 reg_write_data[15:0] $end
$var reg 3 8 reg_read_addr_1[2:0] $end
$var reg 16 9 reg_read_data_1[15:0] $end
$var reg 3 : reg_read_addr_2[2:0] $end
$var reg 16 ; reg_read_data_2[15:0] $end
$var reg 16 < sign_ext_im[15:0] $end
$var reg 16 = read_data2[15:0] $end
$var reg 16 > zero_ext_im[15:0] $end
$var reg 16 ? imm_ext[15:0] $end
$var reg 1 @ jrcontrol $end
$var reg 3 A alu_control[2:0] $end
$var reg 16 B alu_out[15:0] $end
$var reg 1 C zero_flag $end
$var reg 1 D carry_flag $end
$var reg 16 E im_shift_1[15:0] $end
$var reg 16 F pc_j[15:0] $end
$var reg 16 G pc_beq[15:0] $end
$var reg 16 H pc_4beq[15:0] $end
$var reg 16 I pc_4beqj[15:0] $end
$var reg 16 J pc_jr[15:0] $end
$var reg 1 K beq_control $end
$var reg 15 L jump_shift_1[14:0] $end
$var reg 16 M ar[15:0] $end
$var reg 16 N mem_read_data[15:0] $end
$var reg 16 O no_sign_ext[15:0] $end
$var reg 1 P sign_or_zero $end
$var reg 7 Q tmp1[6:0] $end
$var reg 10 R tmp2[9:0] $end
$var reg 16 S z[15:0] $end
$var reg 8 T fr[7:0] $end
$scope module instruction_memory $end
$var reg 16 U pc[15:0] $end
$var reg 16 V instruction[15:0] $end
$var reg 4 W rom_addr[3:0] $end
$upscope $end
$scope module control $end
$var reg 4 X opcode[3:0] $end
$var reg 1 Y reset $end
$var reg 2 Z reg_dst[1:0] $end
$var reg 2 [ mem_to_reg[1:0] $end
$var reg 2 \ alu_op[1:0] $end
$var reg 1 ] jump $end
$var reg 1 ^ branch $end
$var reg 1 _ mem_read $end
$var reg 1 ` mem_write $end
$var reg 1 a alu_src $end
$var reg 1 b reg_write $end
$var reg 1 c sign_or_zero $end
$upscope $end
$scope module register_file $end
$var reg 1 d clk $end
$var reg 1 e rst $end
$var reg 1 f reg_write_en $end
$var reg 3 g reg_write_dest[2:0] $end
$var reg 16 h reg_write_data[15:0] $end
$var reg 3 i reg_read_addr_1[2:0] $end
$var reg 16 j reg_read_data_1[15:0] $end
$var reg 3 k reg_read_addr_2[2:0] $end
$var reg 16 l reg_read_data_2[15:0] $end
$comment reg_array is not handled $end
$upscope $end
$scope module alucontrol $end
$var reg 3 m alu_select[2:0] $end
$var reg 2 n aluop[1:0] $end
$var reg 3 o funct[2:0] $end
$upscope $end
$scope module alu $end
$var reg 16 p inp_a[15:0] $end
$var reg 16 q inp_b[15:0] $end
$var reg 3 r sel[2:0] $end
$var reg 16 s out_alu[15:0] $end
$var reg 1 t zero_flag $end
$var reg 1 u carry_flag $end
$var reg 17 v result[16:0] $end
$upscope $end
$scope module data_memory $end
$var reg 1 w clk $end
$var reg 16 x mem_access_addr[15:0] $end
$var reg 16 y mem_write_data[15:0] $end
$var reg 1 z mem_write_en $end
$var reg 1 { mem_read $end
$var reg 16 | mem_read_data[15:0] $end
$var integer 32 } i $end
$var reg 8 !" ram_addr[7:0] $end
$comment ram is not handled $end
$upscope $end
$upscope $end
$upscope $end
$enddefinitions $end
#0
0!
1"
b0000000000000000 #
b0000000000000000 $
0%
1&
b0000000000000000 '
b0000000000000000 (
b0000000000000000 )
b0000000000000001 *
b0000000000000001 +
b0111001000000101 ,
b00 -
b00 .
b00 /
00
01
02
03
04
05
b001 6
b0000000000000000 7
b000 8
b0000000000000000 9
b001 :
b0000000000000000 ;
b0000000000000101 <
b0000000000000000 =
b0000000000000101 >
b0000000000000101 ?
0@
b101 A
b0000000000000000 B
1C
0D
bUUUUUUUUUUUUUUUU E
bUUUUUUUUUUUUUUUU F
b0000000000000001 G
bUUUUUUUUUUUUUUUU H
bUUUUUUUUUUUUUUUU I
bUUUUUUUUUUUUUUUU J
0K
b110010000001010 L
b0000000000000101 M
b0000000000000000 N
bUUUUUUUUUUUUUUUU O
1P
b0000000 Q
b0000000000 R
b0000000000000001 S
bUUUUUUUU T
b0000000000000000 U
b0111001000000101 V
b0000 W
b0111 X
1Y
b00 Z
b00 [
b00 \
0]
0^
0_
0`
0a
0b
1c
0d
1e
0f
b001 g
b0000000000000000 h
b000 i
b0000000000000000 j
b001 k
b0000000000000000 l
b101 m
b00 n
b101 o
b0000000000000000 p
b0000000000000000 q
b101 r
b0000000000000000 s
1t
0u
b00000000000000000 v
0w
b0000000000000101 x
b0000000000000000 y
0z
0{
b0000000000000000 |
b10000000000000000000000000000000 }
b00000101 !"
#5000000
1!
1%
1d
1w
#10000000
0!
0%
0d
0w
#15000000
1!
1%
1d
1w
#20000000
0!
0"
b0000000000000101 $
0%
0&
b0000000000000101 (
b11 -
b11 /
12
14
15
b0000000000000101 7
b0000000000000101 =
b000 A
b0000000000000101 B
0C
0Y
b11 Z
b11 \
1_
1a
1b
0d
0e
1f
b0000000000000101 h
b000 m
b11 n
b0000000000000101 q
b000 r
b0000000000000101 s
0t
b00000000000000101 v
0w
1{
#25000000
1!
b0000000000000001 #
b0000000000000000 $
1%
b0000000000000001 '
b0000000000000000 (
b0000000000000001 )
b0000000000000010 *
b0000000000000010 +
b0111010000000000 ,
b010 6
b0000000000000000 7
b010 :
b0000000000000000 ;
b0000000000000000 <
b0000000000000000 =
b0000000000000000 >
b0000000000000000 ?
b0000000000000000 B
1C
b0000000000000010 G
b110100000000000 L
b0000000000000000 M
b0000000000000001 U
b0111010000000000 V
b0001 W
1d
b010 g
b0000000000000000 h
b010 k
b0000000000000000 l
b000 o
b0000000000000000 q
b0000000000000000 s
1t
b00000000000000000 v
1w
b0000000000000000 x
b0000000000000000 y
b00000000 !"
#30000000
0!
0%
0d
0w
#35000000
1!
b0000000000000010 #
1%
b0000000000000010 '
b0000000000000010 )
b0000000000000011 *
b0000000000000011 +
b0111011000000000 ,
b011 6
b011 :
b0000000000000011 G
b110110000000000 L
b0000000000000010 U
b0111011000000000 V
b0010 W
1d
b011 g
b011 k
1w
#40000000
0!
0%
0d
0w
#45000000
1!
b0000000000000011 #
1%
b0000000000000011 '
b0000000000000011 )
b0000000000000100 *
b0000000000000100 +
b0111100000000000 ,
b100 6
b100 :
b0000000000000100 G
b111000000000000 L
b0000000000000011 U
b0111100000000000 V
b0011 W
1d
b100 g
b100 k
1w
#50000000
0!
0%
0d
0w
#55000000
1!
b0000000000000100 #
1%
b0000000000000100 '
b0000000000000100 )
b0000000000000101 *
b0000000000000101 +
b0001010011010000 ,
b01 -
b00 /
02
04
b010 6
b011 8
b010 :
b0000000000010000 <
b0000000000010000 >
b0000000000010000 ?
b0000000000000101 G
b010100110100000 L
b0000000011010000 M
bUUUUUU01 T
b0000000000000100 U
b0001010011010000 V
b0100 W
b0001 X
b01 Z
b00 \
0_
0a
1d
b010 g
b011 i
b010 k
b00 n
1w
b0000000011010000 x
0{
b11010000 !"
#60000000
0!
0%
0d
0w
#65000000
1!
b0000000000000101 #
b0000000000000001 $
1%
b0000000000000101 '
b0000000000000001 (
b0000000000000101 )
b0000000000000110 *
b0000000000000110 +
b0001000011011110 ,
b011 6
b0000000000000001 7
b000 :
b0000000000011110 <
b0000000000011110 >
b0000000000011110 ?
b110 A
b0000000000000001 B
0C
b0000000000000110 G
b010000110111100 L
b0000000011011110 M
bUUUUUU00 T
b0000000000000101 U
b0001000011011110 V
b0101 W
1d
b011 g
b0000000000000001 h
b000 k
b110 m
b110 o
b110 r
b0000000000000001 s
0t
b00000000000000001 v
1w
b0000000011011110 x
b11011110 !"
#70000000
0!
0%
0d
0w
#75000000
1!
b0000000000000110 #
b0000000000000001 $
1%
b0000000000000110 '
b0000000000000001 (
b0000000000000110 )
b0000000000000111 *
b0000000000000111 +
b0001000100100110 ,
b100 6
b0000000000000001 7
b100 8
b0000000000000000 9
b1111111111100110 <
b0000000000100110 >
b1111111111100110 ?
b0000000000000001 B
b0000000000000111 G
b010001001001100 L
b0000000000100110 M
b1111111 Q
b1111111111 R
b0000000000000110 U
b0001000100100110 V
b0110 W
1d
b100 g
b0000000000000001 h
b100 i
b0000000000000000 j
b0000000000000000 p
b0000000000000001 s
b00000000000000001 v
1w
b0000000000100110 x
b00100110 !"
#80000000
0!
0%
0d
0w
#85000000
1!
b0000000000000111 #
b0000000000000100 $
1%
b0000000000000111 '
b0000000000000100 (
b0000000000000111 )
b0000000000000100 *
b0000000000001000 +
b1011011001000100 ,
b00 -
b01 /
11
05
b011 6
b0000000000000100 7
b001 8
b0000000000000101 9
b011 :
b0000000000000001 ;
b0000000000000100 <
b0000000000000001 =
b0000000000000100 >
b0000000000000100 ?
b001 A
b0000000000000100 B
0C
b0000000000000100 G
1K
b110110010001000 L
b0000000001000100 M
b0000000 Q
b0000000000 R
b0000000000000111 U
b1011011001000100 V
b0111 W
b1011 X
b00 Z
b01 \
1^
0b
1d
0f
b011 g
b0000000000000100 h
b001 i
b0000000000000101 j
b011 k
b0000000000000001 l
b001 m
b01 n
b100 o
b0000000000000101 p
b0000000000000001 q
b001 r
b0000000000000100 s
0t
b00000000000000100 v
1w
b0000000001000100 x
b0000000000000001 y
b01000100 !"
#90000000
0!
0%
0d
0w
#95000000
1!
b0000000000000100 #
b0000000000000001 $
1%
b0000000000000100 '
b0000000000000001 (
b0000000000000100 )
b0000000000000101 *
b0000000000000101 +
b0001010011010000 ,
b01 -
b00 /
01
15
b010 6
b0000000000000001 7
b011 8
b0000000000000001 9
b010 :
b0000000000000000 ;
b0000000000010000 <
b0000000000000000 =
b0000000000010000 >
b0000000000010000 ?
b000 A
b0000000000000001 B
b0000000000000101 G
0K
b010100110100000 L
b0000000011010000 M
b0000000000000100 U
b0001010011010000 V
b0100 W
b0001 X
b01 Z
b00 \
0^
1b
1d
1f
b010 g
b0000000000000001 h
b011 i
b0000000000000001 j
b010 k
b0000000000000000 l
b000 m
b00 n
b000 o
b0000000000000001 p
b0000000000000000 q
b000 r
b0000000000000001 s
b00000000000000001 v
1w
b0000000011010000 x
b0000000000000000 y
b11010000 !"
#100000000
0!
0%
0d
0w
#105000000
1!
b0000000000000101 #
b0000000000000010 $
1%
b0000000000000101 '
b0000000000000010 (
b0000000000000101 )
b0000000000000110 *
b0000000000000110 +
b0001000011011110 ,
b011 6
b0000000000000010 7
b000 :
b0000000000000000 ;
b0000000000011110 <
b0000000000000000 =
b0000000000011110 >
b0000000000011110 ?
b110 A
b0000000000000010 B
b0000000000000110 G
b010000110111100 L
b0000000011011110 M
b0000000000000101 U
b0001000011011110 V
b0101 W
1d
b011 g
b0000000000000010 h
b000 k
b0000000000000000 l
b110 m
b110 o
b0000000000000000 q
b110 r
b0000000000000010 s
b00000000000000010 v
1w
b0000000011011110 x
b0000000000000000 y
b11011110 !"
#110000000
0!
0%
0d
0w
#115000000
1!
b0000000000000110 #
b0000000000000010 $
1%
b0000000000000110 '
b0000000000000010 (
b0000000000000110 )
b0000000000000111 *
b0000000000000111 +
b0001000100100110 ,
b100 6
b0000000000000010 7
b100 8
b0000000000000001 9
b1111111111100110 <
b0000000000100110 >
b1111111111100110 ?
b0000000000000010 B
b0000000000000111 G
b010001001001100 L
b0000000000100110 M
b1111111 Q
b1111111111 R
b0000000000000110 U
b0001000100100110 V
b0110 W
1d
b100 g
b0000000000000010 h
b100 i
b0000000000000001 j
b0000000000000001 p
b0000000000000010 s
b00000000000000010 v
1w
b0000000000100110 x
b00100110 !"
#120000000
0!
0%
0d
0w
